MANIFEST.in
README
setup.cfg
setup.py
icdMapping/__init__.py
icdMapping/icd2map.py
icdMapping.egg-info/PKG-INFO
icdMapping.egg-info/SOURCES.txt
icdMapping.egg-info/dependency_links.txt
icdMapping.egg-info/requires.txt
icdMapping.egg-info/top_level.txt
icdMapping/res/icd10_map_ahrq.json
icdMapping/res/icd10_map_ahrq_pcs.json
icdMapping/res/icd10_map_cc.json
icdMapping/res/icd10_map_ccs.json
icdMapping/res/icd10_map_charlson.json
icdMapping/res/icd10_map_elix.json
icdMapping/res/icd10_map_names_ccs.json
icdMapping/res/icd10_map_pccc_dx.json
icdMapping/res/icd10_map_pccc_pcs.json
icdMapping/res/icd10_map_quan_deyo.json
icdMapping/res/icd10_map_quan_elix.json
icdMapping/res/icd10_sub_chapters.json
icdMapping/res/icd9_majors.json
icdMapping/res/icd9_map_ahrq.json
icdMapping/res/icd9_map_cc.json
icdMapping/res/icd9_map_charlson.json
icdMapping/res/icd9_map_elix.json
icdMapping/res/icd9_map_multi_ccs.json
icdMapping/res/icd9_map_pccc_dx.json
icdMapping/res/icd9_map_pccc_pcs.json
icdMapping/res/icd9_map_quan_deyo.json
icdMapping/res/icd9_map_quan_elix.json
icdMapping/res/icd9_map_single_ccs.json
icdMapping/res/icd9_names_multi_ccs.json
icdMapping/res/icd9_names_single_ccs.json
icdMapping/res/icd9cm2014_leaf.json
icdMapping/res/icd9cm_hierarchy.json
icdMapping/res/icd_map_cc_hcc.json