Metadata-Version: 1.1
Name: icdMapping
Version: 0.12
Summary: Identify diseases from ICD code list
Home-page: https://github.com/Luyaochen1/icdMapping
Author: Xiaoqian Jiang, Luyao Chen
Author-email: your.email@domain.com
License: MIT
Download-URL: https://github.com/Luyaochen1/icdMapping/archive/v0.12.tar.gz
Keywords: icd 9,icd 10,diseases
Platform: UNKNOWN
Classifier: Development Status :: 3 - Alpha
Classifier: Intended Audience :: Developers
Classifier: Topic :: Software Development :: Build Tools
Classifier: License :: OSI Approved :: MIT License
Classifier: Programming Language :: Python :: 3
Classifier: Programming Language :: Python :: 3.4
Classifier: Programming Language :: Python :: 3.5
Classifier: Programming Language :: Python :: 3.6
Classifier: Programming Language :: Python :: 3.7
Classifier: Programming Language :: Python :: 3.8
